pydirectinput/__init__.py
pydirectinput/py.typed
pydirectinput_rgx-2.1.3.dist-info/licenses/LICENSE.txt
pydirectinput_rgx-2.1.3.dist-info/METADATA
pydirectinput_rgx-2.1.3.dist-info/WHEEL
pydirectinput_rgx-2.1.3.dist-info/top_level.txt
pydirectinput_rgx-2.1.3.dist-info/RECORD
