Metadata-Version: 2.4
Name: pydirectinput_rgx
Version: 2.1.3
Summary: Python mouse and keyboard input automation for Windows using Direct Input.
Author-email: ReggX <dev@reggx.eu>
License-Expression: MIT
Project-URL: Homepage, https://github.com/reggx/pydirectinput_rgx
Keywords: python,directinput,wrapper,abstraction,input,mouse,keyboard,automation
Classifier: Development Status :: 5 - Production/Stable
Classifier: Environment :: Win32 (MS Windows)
Classifier: Intended Audience :: Developers
Classifier: Operating System :: Microsoft :: Windows
Classifier: Programming Language :: Python :: 3
Classifier: Programming Language :: Python :: 3 :: Only
Classifier: Programming Language :: Python :: 3.7
Classifier: Programming Language :: Python :: 3.8
Classifier: Programming Language :: Python :: 3.9
Classifier: Programming Language :: Python :: 3.10
Classifier: Programming Language :: Python :: 3.11
Classifier: Programming Language :: Python :: 3.12
Classifier: Programming Language :: Python :: 3.13
Classifier: Programming Language :: Python :: 3.14
Classifier: Topic :: Software Development :: Libraries
Classifier: Typing :: Typed
Requires-Python: >=3.7
License-File: LICENSE.txt
Requires-Dist: typing-extensions>=4.2.0; python_version < "3.9"
Dynamic: license-file
